setoptconf/__init__.py
setoptconf/config.py
setoptconf/datatype.py
setoptconf/exception.py
setoptconf/manager.py
setoptconf/setting.py
setoptconf/util.py
setoptconf/__pycache__/__init__.cpython-39.pyc
setoptconf/__pycache__/config.cpython-39.pyc
setoptconf/__pycache__/datatype.cpython-39.pyc
setoptconf/__pycache__/exception.cpython-39.pyc
setoptconf/__pycache__/manager.cpython-39.pyc
setoptconf/__pycache__/setting.cpython-39.pyc
setoptconf/__pycache__/util.cpython-39.pyc
setoptconf/source/__init__.py
setoptconf/source/base.py
setoptconf/source/commandline.py
setoptconf/source/configfile.py
setoptconf/source/environment.py
setoptconf/source/filebased.py
setoptconf/source/jsonfile.py
setoptconf/source/mapping.py
setoptconf/source/modobj.py
setoptconf/source/yamlfile.py
setoptconf/source/__pycache__/__init__.cpython-39.pyc
setoptconf/source/__pycache__/base.cpython-39.pyc
setoptconf/source/__pycache__/commandline.cpython-39.pyc
setoptconf/source/__pycache__/configfile.cpython-39.pyc
setoptconf/source/__pycache__/environment.cpython-39.pyc
setoptconf/source/__pycache__/filebased.cpython-39.pyc
setoptconf/source/__pycache__/jsonfile.cpython-39.pyc
setoptconf/source/__pycache__/mapping.cpython-39.pyc
setoptconf/source/__pycache__/modobj.cpython-39.pyc
setoptconf/source/__pycache__/yamlfile.cpython-39.pyc
setoptconf_tmp-0.3.1.dist-info/LICENSE
setoptconf_tmp-0.3.1.dist-info/METADATA
setoptconf_tmp-0.3.1.dist-info/WHEEL
setoptconf_tmp-0.3.1.dist-info/top_level.txt
setoptconf_tmp-0.3.1.dist-info/RECORD
