Metadata-Version: 2.1
Name: setoptconf-tmp
Version: 0.3.1
Summary: A module for retrieving program settings from various sources in a consistant method.
Home-page: https://github.com/carlio/setoptconf-tmp
Author: Jason Simeone
Author-email: jay@classless.net
Maintainer: Carl Crowder
Maintainer-email: git@carlcrowder.com
License: MIT
Keywords: settings,options,configuration,config,arguments
Platform: UNKNOWN
Classifier: Development Status :: 4 - Beta
Classifier: Intended Audience :: Developers
Classifier: License :: OSI Approved :: MIT License
Classifier: Operating System :: OS Independent
Classifier: Programming Language :: Python :: 3.6
Classifier: Programming Language :: Python :: 3.7
Classifier: Programming Language :: Python :: 3.8
Classifier: Programming Language :: Python :: 3.9
Classifier: Topic :: Software Development :: Libraries :: Python Modules
Provides-Extra: YAML
License-File: LICENSE
